healformers/__init__.py
healformers/models/__init__.py
healformers/models/hf_models.py
healformers/toolbox/__init__.py
healformers/toolbox/mock.py
healformers-0.1.1.dist-info/METADATA
healformers-0.1.1.dist-info/WHEEL
healformers-0.1.1.dist-info/top_level.txt
healformers-0.1.1.dist-info/RECORD
