Metadata-Version: 2.4
Name: healformers
Version: 0.1.1
Summary: Mask-Aware HEALPix Transformers
Author: lalalabox
License-Expression: Apache-2.0
Project-URL: Homepage, https://github.com/lalalabox/healformers
Project-URL: Repository, https://github.com/lalalabox/healformers
Project-URL: Documentation, https://github.com/lalalabox/healformers#readme
Keywords: healpix,healpy,transformers,astronomy,deep learning
Classifier: Programming Language :: Python :: 3
Classifier: Programming Language :: Python :: 3.11
Classifier: Operating System :: OS Independent
Classifier: Intended Audience :: Science/Research
Classifier: Topic :: Scientific/Engineering :: Astronomy
Classifier: Topic :: Scientific/Engineering :: Artificial Intelligence
Requires-Python: >=3.11
Requires-Dist: pyccl>=3.1
Requires-Dist: healpy>=1.17
Requires-Dist: loguru>=0.7
Requires-Dist: torch<2.7,>=2.1
Requires-Dist: transformers>=4.45
